README.md
setup.cfg
setup.py
HPCC_bitcoin_parser/__init__.py
HPCC_bitcoin_parser/address.py
HPCC_bitcoin_parser/block.py
HPCC_bitcoin_parser/block_header.py
HPCC_bitcoin_parser/blockchain.py
HPCC_bitcoin_parser/index.py
HPCC_bitcoin_parser/input.py
HPCC_bitcoin_parser/output.py
HPCC_bitcoin_parser/script.py
HPCC_bitcoin_parser/transaction.py
HPCC_bitcoin_parser/utils.py
HPCC_bitcoin_parser.egg-info/PKG-INFO
HPCC_bitcoin_parser.egg-info/SOURCES.txt
HPCC_bitcoin_parser.egg-info/dependency_links.txt
HPCC_bitcoin_parser.egg-info/requires.txt
HPCC_bitcoin_parser.egg-info/top_level.txt
HPCC_bitcoin_parser/tests/__init__.py
HPCC_bitcoin_parser/tests/test_address.py
HPCC_bitcoin_parser/tests/test_block.py
HPCC_bitcoin_parser/tests/test_index.py
HPCC_bitcoin_parser/tests/test_output.py
HPCC_bitcoin_parser/tests/test_script.py
HPCC_bitcoin_parser/tests/test_transaction.py
HPCC_bitcoin_parser/tests/test_utils.py
HPCC_bitcoin_parser/tests/utils.py