Metadata-Version: 1.1
Name: HPCC-bitcoin-parser
Version: 0.1.5
Summary: Bitcoin blockchain parser
Home-page: https://github.com/Invictus-ill/HPCC_blockchain_parser.git
Author: Rohan Maheshwari
Author-email: therohanm@gmail.com
License: UNKNOWN
Platform: UNKNOWN
Classifier: Development Status :: 5 - Production/Stable
Classifier: Environment :: Console
Classifier: Intended Audience :: Developers
Classifier: License :: OSI Approved :: GNU Lesser General Public License v3 (LGPLv3)
Classifier: Topic :: Software Development :: Libraries
